{
  "providers": {
    "awscloudformation": {
      "AuthRoleName": "amplify-frontend-dev-140327-authRole",
      "UnauthRoleArn": "arn:aws:iam::417873687559:role/amplify-frontend-dev-140327-unauthRole",
      "AuthRoleArn": "arn:aws:iam::417873687559:role/amplify-frontend-dev-140327-authRole",
      "Region": "ca-central-1",
      "DeploymentBucketName": "amplify-frontend-dev-140327-deployment",
      "UnauthRoleName": "amplify-frontend-dev-140327-unauthRole",
      "StackName": "amplify-frontend-dev-140327",
      "StackId": "arn:aws:cloudformation:ca-central-1:417873687559:stack/amplify-frontend-dev-140327/d8f6f770-6cf3-11ed-a2c1-02319db53ee2",
      "AmplifyAppId": "d2zivzuy2b8hed",
      "APIGatewayAuthURL": "https://s3.amazonaws.com/amplify-frontend-dev-140327-deployment/amplify-cfn-templates/api/APIGatewayAuthStack.json"
    }
  },
  "auth": {
    "frontend4b6964a2": {
      "service": "Cognito",
      "providerPlugin": "awscloudformation",
      "dependsOn": [],
      "customAuth": false,
      "frontendAuthConfig": {
        "socialProviders": [],
        "usernameAttributes": [
          "EMAIL"
        ],
        "signupAttributes": [
          "EMAIL"
        ],
        "passwordProtectionSettings": {
          "passwordPolicyMinLength": 8,
          "passwordPolicyCharacters": []
        },
        "mfaConfiguration": "OFF",
        "mfaTypes": [
          "SMS"
        ],
        "verificationMechanisms": [
          "EMAIL"
        ]
      },
      "providerMetadata": {
        "s3TemplateURL": "https://s3.amazonaws.com/amplify-frontend-dev-140327-deployment/amplify-cfn-templates/auth/frontend4b6964a2-cloudformation-template.json",
        "logicalId": "authfrontend4b6964a2"
      },
      "lastPushTimeStamp": "2022-11-29T20:37:59.582Z",
      "output": {
        "UserPoolId": "ca-central-1_KGD6gZf9p",
        "AppClientIDWeb": "196ugft6vpothp9okfi68vbp0l",
        "AppClientID": "7jjbt9r5pcps76bqsh8af07t63",
        "IdentityPoolId": "ca-central-1:dbb5d6f0-652d-4f71-acea-c94282242f93",
        "UserPoolArn": "arn:aws:cognito-idp:ca-central-1:417873687559:userpool/ca-central-1_KGD6gZf9p",
        "IdentityPoolName": "frontend4b6964a2_identitypool_4b6964a2__dev",
        "UserPoolName": "frontend4b6964a2_userpool_4b6964a2"
      },
      "lastPushDirHash": "WRLMQnOPYxwwJWFsBzWn8BGanLI="
    }
  },
  "function": {
    "upload": {
      "build": true,
      "providerPlugin": "awscloudformation",
      "service": "Lambda",
      "dependsOn": [
        {
          "category": "storage",
          "resourceName": "uploads",
          "attributes": [
            "Name",
            "Arn"
          ],
          "attributeEnvMap": {
            "Name": "TABLE_NAME",
            "Arn": "TABLE_ARN"
          }
        },
        {
          "category": "storage",
          "resourceName": "uploads",
          "attributes": [
            "Name",
            "Arn",
            "StreamArn"
          ]
        }
      ],
      "lastBuildTimeStamp": "2022-11-29T20:36:47.383Z",
      "lastBuildType": "PROD",
      "lastPackageTimeStamp": "2022-11-29T20:36:50.310Z",
      "distZipFilename": "upload-6943437030344a365459-build.zip",
      "s3Bucket": {
        "deploymentBucketName": "amplify-frontend-dev-140327-deployment",
        "s3Key": "amplify-builds/upload-6943437030344a365459-build.zip"
      },
      "providerMetadata": {
        "s3TemplateURL": "https://s3.amazonaws.com/amplify-frontend-dev-140327-deployment/amplify-cfn-templates/function/upload-cloudformation-template.json",
        "logicalId": "functionupload"
      },
      "lastPushTimeStamp": "2022-11-29T20:37:59.781Z",
      "output": {
        "Region": "ca-central-1",
        "Arn": "arn:aws:lambda:ca-central-1:417873687559:function:upload-dev",
        "Name": "upload-dev",
        "LambdaExecutionRole": "frontendLambdaRole0e9546f1-dev"
      },
      "lastPushDirHash": "ub4Zr5llvQQAj/sMyqULWP3mszs="
    },
    "S3Trigger16ab83d7": {
      "service": "Lambda",
      "providerPlugin": "awscloudformation",
      "build": true,
      "lastBuildTimeStamp": "2022-11-29T16:35:11.030Z",
      "lastBuildType": "PROD",
      "lastPackageTimeStamp": "2022-11-29T16:35:11.052Z",
      "distZipFilename": "S3Trigger16ab83d7-32624f32584d306a6371-build.zip",
      "s3Bucket": {
        "deploymentBucketName": "amplify-frontend-dev-140327-deployment",
        "s3Key": "amplify-builds/S3Trigger16ab83d7-32624f32584d306a6371-build.zip"
      },
      "providerMetadata": {
        "s3TemplateURL": "https://s3.amazonaws.com/amplify-frontend-dev-140327-deployment/amplify-cfn-templates/function/S3Trigger16ab83d7-cloudformation-template.json",
        "logicalId": "functionS3Trigger16ab83d7"
      },
      "lastPushTimeStamp": "2022-11-29T20:37:59.588Z",
      "output": {
        "Region": "ca-central-1",
        "Arn": "arn:aws:lambda:ca-central-1:417873687559:function:S3Trigger16ab83d7-dev",
        "Name": "S3Trigger16ab83d7-dev",
        "LambdaExecutionRole": "S3Trigger16ab83d7LambdaRole16ab83d7-dev"
      },
      "lastPushDirHash": "iWzRgM04wEu8V/3x6o9BnfYDhJo="
    }
  },
  "storage": {
    "frontent": {
      "service": "S3",
      "providerPlugin": "awscloudformation",
      "dependsOn": [
        {
          "category": "function",
          "resourceName": "S3Trigger16ab83d7",
          "attributes": [
            "Name",
            "Arn",
            "LambdaExecutionRole"
          ]
        }
      ],
      "lastPushTimeStamp": "2022-11-29T20:41:15.847Z",
      "providerMetadata": {
        "s3TemplateURL": "https://s3.amazonaws.com/amplify-frontend-dev-140327-deployment/amplify-cfn-templates/storage/cloudformation-template.json",
        "logicalId": "storagefrontent"
      },
      "output": {
        "BucketName": "uload-images-sample140327-dev",
        "Region": "ca-central-1"
      },
      "lastPushDirHash": "OvkqxG+806IK452zWO1K8hpoXpk="
    },
    "uploads": {
      "service": "DynamoDB",
      "providerPlugin": "awscloudformation",
      "providerMetadata": {
        "s3TemplateURL": "https://s3.amazonaws.com/amplify-frontend-dev-140327-deployment/amplify-cfn-templates/storage/uploads-cloudformation-template.json",
        "logicalId": "storageuploads"
      },
      "lastPushTimeStamp": "2022-11-29T20:37:59.595Z",
      "output": {
        "PartitionKeyName": "id",
        "SortKeyName": "uid",
        "SortKeyType": "S",
        "Region": "ca-central-1",
        "Arn": "arn:aws:dynamodb:ca-central-1:417873687559:table/uploads-dev",
        "StreamArn": "arn:aws:dynamodb:ca-central-1:417873687559:table/uploads-dev/stream/2022-11-28T05:09:13.911",
        "PartitionKeyType": "S",
        "Name": "uploads-dev"
      },
      "lastPushDirHash": "HjCsz1V12xugsRtYl/mQrslR9NA="
    }
  },
  "api": {
    "uploadsapi": {
      "service": "API Gateway",
      "providerPlugin": "awscloudformation",
      "dependsOn": [
        {
          "category": "function",
          "resourceName": "upload",
          "attributes": [
            "Name",
            "Arn"
          ]
        }
      ],
      "providerMetadata": {
        "s3TemplateURL": "https://s3.amazonaws.com/amplify-frontend-dev-140327-deployment/amplify-cfn-templates/api/uploadsapi-cloudformation-template.json",
        "logicalId": "apiuploadsapi"
      },
      "lastPushTimeStamp": "2022-11-29T20:37:59.597Z",
      "output": {
        "ApiName": "uploadsapi",
        "RootUrl": "https://a4pajp1arb.execute-api.ca-central-1.amazonaws.com/dev",
        "ApiId": "a4pajp1arb"
      },
      "lastPushDirHash": "FjIZR0KJEzkzj7VYj/bBuh6b3W8="
    }
  }
}